puwifi.py
puwifi-1.1.2.dist-info/LICENSE
puwifi-1.1.2.dist-info/METADATA
puwifi-1.1.2.dist-info/WHEEL
puwifi-1.1.2.dist-info/entry_points.txt
puwifi-1.1.2.dist-info/top_level.txt
puwifi-1.1.2.dist-info/RECORD
