Metadata-Version: 2.1
Name: puwifi
Version: 1.1.2
Summary: ⚡ A script made to automate the wifi login process to Parul university routers. login to wifi forever
Author-email: SaicharanKandukuri <saicharankandukuri1x1@gmail.com>
Project-URL: Homepage, https://github.com/SaicharanKandukuri/puwifi
Project-URL: Bug Tracker, https://github.com/SaicharanKandukuri/puwifi/issues
Classifier: Programming Language :: Python :: 3
Classifier: License :: OSI Approved :: MIT License
Classifier: Operating System :: OS Independent
Requires-Python: >=3.0
License-File: LICENSE
Requires-Dist: requests
Requires-Dist: rich
Requires-Dist: argparse
